{"map_file_path": "grid_maps/Ihlen/occ_grid_small.txt", "start_pos": [15, 53], "goal_pos": [61, 3], "robot_rows": [15, 15, 16, 18, 21, 24, 27, 30, 33, 36, 39, 42, 45, 47, 48, 49, 50, 50, 50, 50, 50, 50, 50, 50, 50, 50, 50, 50, 50, 50, 50, 50, 51, 53, 55, 57, 59, 60, 60, 60, 60, 60, 60, 60, 60, 60, 60, 60, 60, 60, 60, 60, 60, 61, 61, 61, 61, 61, 61], "robot_cols": [53, 53, 53, 53, 53, 53, 53, 53, 53, 53, 53, 53, 53, 53, 53, 53, 53, 53, 53, 52, 50, 48, 45, 42, 39, 36, 33, 30, 28, 27, 27, 27, 27, 27, 27, 27, 27, 27, 27, 27, 26, 24, 21, 18, 15, 12, 9, 6, 4, 2, 1, 1, 1, 1, 1, 1, 2, 3, 3], "robot_speeds": [0, 0, 1, 2, 3, 3, 3, 3, 3, 3, 3, 3, 3, 2, 1, 1, 1, 0, 0, 1, 2, 2, 3, 3, 3, 3, 3, 3, 2, 1, 0, 0, 1, 2, 2, 2, 2, 1, 0, 0, 1, 2, 3, 3, 3, 3, 3, 3, 2, 2, 1, 0, 0, 1, 0, 0, 1, 1, 0], "robot_directions": [0, 3, 3, 3, 3, 3, 3, 3, 3, 3, 3, 3, 3, 3, 3, 3, 3, 3, 0, 0, 0, 0, 0, 0, 0, 0, 0, 0, 0, 0, 0, 3, 3, 3, 3, 3, 3, 3, 3, 0, 0, 0, 0, 0, 0, 0, 0, 0, 0, 0, 0, 0, 3, 3, 3, 2, 2, 2, 2], "action_accs": [0, 1, 1, 1, 0, 0, 0, 0, 0, 0, 0, 0, -1, -1, 0, 0, -1, 0, 1, 1, 0, 1, 0, 0, 0, 0, 0, -1, -1, -1, 0, 1, 1, 0, 0, 0, -1, -1, 0, 1, 1, 1, 0, 0, 0, 0, 0, -1, 0, -1, -1, 0, 1, -1, 0, 1, 0, -1], "action_rots": [-1, 0, 0, 0, 0, 0, 0, 0, 0, 0, 0, 0, 0, 0, 0, 0, 0, 1, 0, 0, 0, 0, 0, 0, 0, 0, 0, 0, 0, 0, -1, 0, 0, 0, 0, 0, 0, 0, 1, 0, 0, 0, 0, 0, 0, 0, 0, 0, 0, 0, 0, -1, 0, 0, -1, 0, 0, 0], "steps": 58, "is_goal": true}